<record id="citation" type="authority">
    <instances id="citation">
        <instance id="citation-citation">
            <web-url>citation</web-url>
            <title-ref>citation</title-ref>
            <title>Local Citations</title>
            <nptAllowed>false</nptAllowed>
        </instance>
        <instance id="citation-worldcat">
            <web-url>worldcat</web-url>
            <title-ref>worldcat</title-ref>
            <title>WorldCat Citations</title>
            <nptAllowed>false</nptAllowed>
        </instance>
    </instances>
</record>

